flake8_svg_badge/__init__.py
flake8_svg_badge/reporter.py
flake8_svg_badge-0.1.0.dist-info/AUTHORS.rst
flake8_svg_badge-0.1.0.dist-info/LICENSE
flake8_svg_badge-0.1.0.dist-info/METADATA
flake8_svg_badge-0.1.0.dist-info/WHEEL
flake8_svg_badge-0.1.0.dist-info/entry_points.txt
flake8_svg_badge-0.1.0.dist-info/top_level.txt
flake8_svg_badge-0.1.0.dist-info/RECORD
