Metadata-Version: 2.1
Name: flake8-svg-badge
Version: 0.1.0
Summary: Svg badge that shows % of problem-free code
Home-page: https://github.com/ribozz/flake8-svg-badge
Author: Alex Rudakov
Author-email: ribozz@gmail.com
License: MIT
Keywords: flake8-svg-badge
Platform: UNKNOWN
Classifier: Development Status :: 2 - Pre-Alpha
Classifier: Intended Audience :: Developers
Classifier: License :: OSI Approved :: MIT License
Classifier: Natural Language :: English
Classifier: Programming Language :: Python :: 2
Classifier: Programming Language :: Python :: 2.6
Classifier: Programming Language :: Python :: 2.7
Classifier: Programming Language :: Python :: 3
Classifier: Programming Language :: Python :: 3.3
Classifier: Programming Language :: Python :: Implementation :: PyPy
Requires-Dist: flake8 (>3.0.0)
